Tabla1SOP/Tabla1SOP.v
module Tabla1SOP();
  wire nA, nB, nC, a1O, a2O, a3O, a4O, a5O, YOut;
  reg A1, B1, C1;
  not n1 (nA, A1);
  not n2 (nB, B1);
  not n3 (nC, C1);
  and a1 (a1O, nA, nB, nC);
  and a2 (a2O, nA, B1, nC);
  and a3 (a3O, A1, nB, nC);
  and a4 (a4O, A1, nB, C1);
  and a5 (a5O, A1, B1, C1);
  or o1 (YOut, a1O, a2O, a3O, a4O, a5O);

  initial begin
      $display ("A B C | Y");
      $display ("=========");
      $monitor ("%b %b %b | %b", A1, B1, C1, YOut);
      A1 = 0; B1 = 0 ; C1 = 0;
      #1 C1 = 1;
      #1 B1 = 1; C1 = 0;
      #1 C1 = 1;
      #1 A1 = 1; B1 = 0; C1 = 0;
      #1 C1 = 1;
      #1 B1 = 1; C1 = 0;
      #1 C1 = 1;
  end
  initial
    begin
      $dumpfile("Tabla1SOP_tb.vcd");
      $dumpvars(0, Tabla1SOP); 
    end
endmodule

Tabla1SOP/Tabla1SOP_tb.vcd
$date
	Thu Jul 30 19:39:03 2020
$end
$version
	Icarus Verilog
$end
$timescale
	1ps
$end
$scope module Tabla1SOP $end
$var wire 1 ! YOut $end
$var wire 1 " a1O $end
$var wire 1 # a2O $end
$var wire 1 $ a3O $end
$var wire 1 % a4O $end
$var wire 1 & a5O $end
$var wire 1 ' nA $end
$var wire 1 ( nB $end
$var wire 1 ) nC $end
$var reg 1 * A1 $end
$var reg 1 + B1 $end
$var reg 1 , C1 $end
$upscope $end
$enddefinitions $end
#0
$dumpvars
0,
0+
0*
1)
1(
1'
0&
0%
0$
0#
1"
1!
$end
#1
0!
0"
0)
1,
#2
1!
1#
1)
0(
0,
1+
#3
0!
0#
0)
1,
#4
1!
1$
1)
1(
0'
0,
0+
1*
#5
0$
1%
0)
1,
#6
0!
0%
1)
0(
0,
1+
#7
1!
1&
0)
1,
