Tabla1POS/Tabla1POS.v
module Tabla1POS();
  wire nA, nB, nC, O1, O2, O3, OutAnd;
  reg A, B, C;
  not U1 (nA, A);
  not U2 (nB, B);
  not U3 (nC, C);
  or U4 (O1, A, B, nC);
  or U5 (O2, A, nB, nC);
  or U6 (O3, nA, nB, C);
  and a1 (OutAnd, O1, O2, O3);

  initial begin
    $display ("A B C | Y");
    $display ("=========");
    $monitor ("%b %b %b | %b", A, B, C, OutAnd);
    A = 0; B = 0; C = 0;
    #1 C = 1;
    #1 B = 1; C = 0;
    #1 C = 1;
    #1 A = 1; B = 0; C = 0;
    #1 C = 1;
    #1 B = 1; C = 0;
    #1 C = 1;
    #1 $finish;
  end

  initial begin
    $dumpfile ("Tabla1POS_tb.vcd");
    $dumpvars (0, Tabla1POS);
    end
endmodule

Tabla1POS/Tabla1POS_tb.vcd
$date
	Thu Jul 30 20:25:14 2020
$end
$version
	Icarus Verilog
$end
$timescale
	1ps
$end
$scope module Tabla1POS $end
$var wire 1 ! O1 $end
$var wire 1 " O2 $end
$var wire 1 # O3 $end
$var wire 1 $ OutAnd $end
$var wire 1 % nA $end
$var wire 1 & nB $end
$var wire 1 ' nC $end
$var reg 1 ( A $end
$var reg 1 ) B $end
$var reg 1 * C $end
$upscope $end
$enddefinitions $end
#0
$dumpvars
0*
0)
0(
1'
1&
1%
1$
1#
1"
1!
$end
#1
0$
0!
0'
1*
#2
1$
1'
1!
0&
0*
1)
#3
0$
0"
0'
1*
#4
1$
1'
1&
1"
0%
0*
0)
1(
#5
0'
1*
#6
0$
0#
1'
0&
0*
1)
#7
1$
1#
0'
1*
