Tabla2SOP/Tabla2SOP.v
module Tabla2SOP();
  wire nA, nB, nC, A1, A2, A3, OrOut;
  reg A, B, C;
  not U1 (nA, A);
  not U2 (nB, B);
  not U3 (nC, C);
  and U4 (A1, nA, nB, C);
  and U5 (A2, A, B, nC);
  and U6 (A3, A, B, C);
  or U7 (OrOut, A1, A2, A3);

  initial begin
    $display ("A B C | Y");
    $display ("=========");
    $monitor ("%b %b %b | %b", A, B, C, OrOut);
    A = 0; B = 0; C = 0;
    #1 C = 1;
    #1 B = 1; C = 0;
    #1 C = 1;
    #1 A =1; B = 0; C = 0;
    #1 C = 1;
    #1 B = 1; C = 0;
    #1 C = 1;
    #1 $finish;
  end

  initial begin
    $dumpfile("Tabla2SOP_tb.vcd");
    $dumpvars(0, Tabla2SOP);
  end
endmodule

Tabla2SOP/Tabla2SOP_tb.vcd
$date
	Thu Jul 30 20:55:05 2020
$end
$version
	Icarus Verilog
$end
$timescale
	1ps
$end
$scope module Tabla2SOP $end
$var wire 1 ! A1 $end
$var wire 1 " A2 $end
$var wire 1 # A3 $end
$var wire 1 $ OrOut $end
$var wire 1 % nA $end
$var wire 1 & nB $end
$var wire 1 ' nC $end
$var reg 1 ( A $end
$var reg 1 ) B $end
$var reg 1 * C $end
$upscope $end
$enddefinitions $end
#0
$dumpvars
0*
0)
0(
1'
1&
1%
0$
0#
0"
0!
$end
#1
1$
1!
0'
1*
#2
0$
0!
1'
0&
0*
1)
#3
0'
1*
#4
1'
1&
0%
0*
0)
1(
#5
0'
1*
#6
1$
1"
1'
0&
0*
1)
#7
0"
1#
0'
1*
