Tabla2POS/Tabla2POS.v
module Tabla2POS();
  wire nA, nB, nC, O1, O2, O3, O4, O5, AndOut;
  reg A, B, C;
  not U1 (nA, A);
  not U2 (nB, B);
  not U3 (nC, C);
  or U4 (O1, A, B, C);
  or U5 (O2, A, nB, C);
  or U6 (O3, A, nB, nC);
  or U7 (O4, nA, B, C);
  or U8 (O5, nA, B, nC);
  and U9 (AndOut, O1, O2, O3, O4, O5);

  initial begin
    $display ("A B C | Y");
    $display ("=========");
    $monitor ("%b %b %b | %b", A, B, C, AndOut);
    A = 0; B = 0; C = 0;
    #1 C = 1;
    #1 B = 1; C = 0;
    #1 C = 1;
    #1 A = 1; B = 0; C =0;
    #1 C = 1;
    #1 B = 1; C = 0;
    #1 C = 1;
    #1 $finish;
  end

  initial begin
    $dumpfile("Tabla2POS_tb.vcd");
    $dumpvars(0, Tabla2POS);
end
endmodule

Tabla2POS/Tabla2POS_tb.vcd
$date
	Thu Jul 30 21:13:17 2020
$end
$version
	Icarus Verilog
$end
$timescale
	1ps
$end
$scope module Tabla2POS $end
$var wire 1 ! AndOut $end
$var wire 1 " O1 $end
$var wire 1 # O2 $end
$var wire 1 $ O3 $end
$var wire 1 % O4 $end
$var wire 1 & O5 $end
$var wire 1 ' nA $end
$var wire 1 ( nB $end
$var wire 1 ) nC $end
$var reg 1 * A $end
$var reg 1 + B $end
$var reg 1 , C $end
$upscope $end
$enddefinitions $end
#0
$dumpvars
0,
0+
0*
1)
1(
1'
1&
1%
1$
1#
0"
0!
$end
#1
1!
1"
0)
1,
#2
0!
0#
1)
0(
0,
1+
#3
0$
1#
0)
1,
#4
1)
1&
0%
1(
1$
0'
0,
0+
1*
#5
0&
1%
0)
1,
#6
1!
1)
1&
0(
0,
1+
#7
0)
1,
