Tabla3SOP/Tabla3SOP.v
module Tabla3SOP();
  wire nA, nB, nC, nD, A1, A2, A3, A4, A5, A6, A7, OrOut;
  reg A, B, C, D;
  not U1 (nA, A);
  not U2 (nB, B);
  not U3 (nC, C);
  not U4 (nD, D);
  and U5 (A1, nA, nB, nC, nD);
  and U6 (A2, nA, nB, nC, D);
  and U7 (A3, nA, nB, C, nD);
  and U8 (A4, nA, nB, C, D);
  and U9 (A5, A, nB, nC, nD);
  and U10 (A6, A, nB, C, nD);
  and U11 (A7, A, B, C, nD);
  or U12 (OrOut, A1, A2, A3, A4, A5, A6, A7);

  initial begin
    $display("A B C D | Y");
    $display("===========");
    $monitor("%b %b %b %b | %b", A, B, C, D, OrOut);
    A = 0; B = 0; C = 0; D = 0;
    #1 D = 1;
    #1 C = 1; D = 0;
    #1 D = 1;
    #1 B = 1; C = 0; D = 0;
    #1 D = 1;
    #1 C = 1; D = 0;
    #1 D = 1;
    #1 A = 1; B = 0; C = 0; D = 0;
    #1 D = 1;
    #1 C = 1; D = 0;
    #1 D = 1;
    #1 B = 1; C = 0; D = 0;
    #1 D = 1;
    #1 C = 1; D = 0;
    #1 D = 1;
    #1 $finish;
  end

  initial begin
    $dumpfile("Tabla3SOP_tb.vcd");
    $dumpvars(0, Tabla3SOP);
  end
endmodule

Tabla3SOP/Tabla3SOP_tb.vcd
$date
	Thu Jul 30 21:36:42 2020
$end
$version
	Icarus Verilog
$end
$timescale
	1ps
$end
$scope module Tabla3SOP $end
$var wire 1 ! A1 $end
$var wire 1 " A2 $end
$var wire 1 # A3 $end
$var wire 1 $ A4 $end
$var wire 1 % A5 $end
$var wire 1 & A6 $end
$var wire 1 ' A7 $end
$var wire 1 ( OrOut $end
$var wire 1 ) nA $end
$var wire 1 * nB $end
$var wire 1 + nC $end
$var wire 1 , nD $end
$var reg 1 - A $end
$var reg 1 . B $end
$var reg 1 / C $end
$var reg 1 0 D $end
$upscope $end
$enddefinitions $end
#0
$dumpvars
00
0/
0.
0-
1,
1+
1*
1)
1(
0'
0&
0%
0$
0#
0"
1!
$end
#1
0!
1"
0,
10
#2
1#
0"
1,
0+
00
1/
#3
0#
1$
0,
10
#4
0(
1,
0$
1+
0*
00
0/
1.
#5
0,
10
#6
1,
0+
00
1/
#7
0,
10
#8
1(
1%
1,
1+
1*
0)
00
0/
0.
1-
#9
0(
0%
0,
10
#10
1(
1&
1,
0+
00
1/
#11
0(
0&
0,
10
#12
1,
1+
0*
00
0/
1.
#13
0,
10
#14
1(
1'
1,
0+
00
1/
#15
0(
0'
0,
10
