Tabla4POS/Tabla4POS.v
module Tabla4POS();
  wire nA, nB, nC, nD, O1, O2, O3, O4, O5, O6, O7, O8, O9, AndOut;
  reg A, B, C, D;
  not U1 (nA, A);
  not U2 (nB, B);
  not U3 (nC, C);
  not U4 (nD, D);
  or U5 (O1, A, B, C, nD);
  or U6 (O2, A, nB, C, D);
  or U7 (O3, A, nB, C, nD);
  or U8 (O4, nA, B, C, nD);
  or U9 (O5, nA, B, nC, nD);
  or U10 (O6, nA, nB, C, D);
  or U11 (O7, nA, nB, C, nD);
  or U12 (O8, nA, nB, nC, D);
  or U13 (O9, nA, nB, nC, nD);
  and U14 (AndOut, O1, O2, O3, O4, O5, O6, O7, O8, O9);

  initial begin
    $display("A B C D | Y");
    $display("===========");
    $monitor("%b %b %b %b | %b", A, B, C, D, AndOut);
    A = 0; B = 0; C = 0; D = 0;
    #1 D = 1;
    #1 C = 1; D = 0;
    #1 D = 1;
    #1 B = 1; C = 0; D = 0;
    #1 D = 1;
    #1 C = 1; D = 0;
    #1 D = 1;
    #1 A = 1; B = 0; C = 0; D = 0;
    #1 D = 1;
    #1 C = 1; D = 0;
    #1 D = 1;
    #1 B = 1; C = 0; D = 0;
    #1 D = 1;
    #1 C = 1; D = 0;
    #1 D = 1;
    #1 $finish;
  end

  initial begin
    $dumpfile("Tabla4POS_tb.vcd");
    $dumpvars(0, Tabla4POS);
  end

endmodule

Tabla4POS/Tabla4POS_tb.vcd
$date
	Thu Jul 30 22:17:01 2020
$end
$version
	Icarus Verilog
$end
$timescale
	1ps
$end
$scope module Tabla4POS $end
$var wire 1 ! AndOut $end
$var wire 1 " O1 $end
$var wire 1 # O2 $end
$var wire 1 $ O3 $end
$var wire 1 % O4 $end
$var wire 1 & O5 $end
$var wire 1 ' O6 $end
$var wire 1 ( O7 $end
$var wire 1 ) O8 $end
$var wire 1 * O9 $end
$var wire 1 + nA $end
$var wire 1 , nB $end
$var wire 1 - nC $end
$var wire 1 . nD $end
$var reg 1 / A $end
$var reg 1 0 B $end
$var reg 1 1 C $end
$var reg 1 2 D $end
$upscope $end
$enddefinitions $end
#0
$dumpvars
02
01
00
0/
1.
1-
1,
1+
1*
1)
1(
1'
1&
1%
1$
1#
1"
1!
$end
#1
0!
0"
0.
12
#2
1!
1.
1"
0-
02
11
#3
0.
12
#4
0!
1.
1$
0#
1-
0,
02
01
10
#5
0$
1#
0.
12
#6
1!
1.
1$
0-
02
11
#7
0.
12
#8
1!
1.
1-
1&
1%
1,
0+
02
01
00
1/
#9
0!
0%
0.
12
#10
1!
1.
1%
0-
02
11
#11
0!
0&
0.
12
#12
1.
1(
0'
1-
1&
0,
02
01
10
#13
0(
1'
0.
12
#14
0)
1.
1(
0-
02
11
#15
0*
1)
0.
12
